jtech_installer/__init__.py
jtech_installer/analyzer/__init__.py
jtech_installer/analyzer/environment.py
jtech_installer/assets/.github/chatmodes/analyst.chatmode.md
jtech_installer/assets/.github/chatmodes/architect.chatmode.md
jtech_installer/assets/.github/chatmodes/dev.chatmode.md
jtech_installer/assets/.github/chatmodes/jtech-master.chatmode.md
jtech_installer/assets/.github/chatmodes/jtech-orchestrator.chatmode.md
jtech_installer/assets/.github/chatmodes/pm.chatmode.md
jtech_installer/assets/.github/chatmodes/po.chatmode.md
jtech_installer/assets/.github/chatmodes/qa.chatmode.md
jtech_installer/assets/.github/chatmodes/sm.chatmode.md
jtech_installer/assets/.github/chatmodes/ux-expert.chatmode.md
jtech_installer/assets/.jtech-core/README.md
jtech_installer/assets/.jtech-core/core-config.yml
jtech_installer/assets/.jtech-core/agents/analyst.md
jtech_installer/assets/.jtech-core/agents/architect.md
jtech_installer/assets/.jtech-core/agents/dev.md
jtech_installer/assets/.jtech-core/agents/jtech-master.md
jtech_installer/assets/.jtech-core/agents/jtech-orchestrator.md
jtech_installer/assets/.jtech-core/agents/pm.md
jtech_installer/assets/.jtech-core/agents/po.md
jtech_installer/assets/.jtech-core/agents/qa.md
jtech_installer/assets/.jtech-core/agents/sm.md
jtech_installer/assets/.jtech-core/agents/ux-expert.md
jtech_installer/assets/.jtech-core/agents-teams/team-all.yaml
jtech_installer/assets/.jtech-core/agents-teams/team-fullstack.yaml
jtech_installer/assets/.jtech-core/agents-teams/team-ide-minimal.yaml
jtech_installer/assets/.jtech-core/agents-teams/team-no-ui.yaml
jtech_installer/assets/.jtech-core/chatmodes/analyst.chatmode.md
jtech_installer/assets/.jtech-core/chatmodes/architect.chatmode.md
jtech_installer/assets/.jtech-core/chatmodes/dev.chatmode.md
jtech_installer/assets/.jtech-core/chatmodes/jtech-master.chatmode.md
jtech_installer/assets/.jtech-core/chatmodes/jtech-orchestrator.chatmode.md
jtech_installer/assets/.jtech-core/chatmodes/pm.chatmode.md
jtech_installer-0.3.0.dist-info/METADATA
jtech_installer-0.3.0.dist-info/WHEEL
jtech_installer-0.3.0.dist-info/entry_points.txt
jtech_installer-0.3.0.dist-info/licenses/LICENSE
jtech_installer-0.3.0.dist-info/RECORD
