Metadata-Version: 2.4
Name: jtech-installer
Version: 0.3.0
Summary: Instalador Enterprise para JTECH™ Core Framework - Veolia
Project-URL: Homepage, https://gitlab.com/veolia.com/brasil/jtech/jtech-generative-ai/jtech-installer
Project-URL: Documentation, https://docs.jtech.dev/installer
Project-URL: Repository, https://gitlab.com/veolia.com/brasil/jtech/jtech-generative-ai/jtech-installer
Project-URL: Issues, https://gitlab.com/veolia.com/brasil/jtech/jtech-generative-ai/jtech-installer/-/issues
Author-email: Angelo Vicente Filho <angelo.vicente@veolia.com>
License: Proprietary
License-File: LICENSE
Keywords: automation,cli,framework,installer,jtech,veolia
Classifier: Development Status :: 4 - Beta
Classifier: Intended Audience :: Developers
Classifier: License :: Other/Proprietary License
Classifier: Programming Language :: Python :: 3
Classifier: Programming Language :: Python :: 3.12
Classifier: Topic :: Software Development
Classifier: Topic :: Utilities
Requires-Python: >=3.12.9
Requires-Dist: click>=8.1.0
Requires-Dist: packaging>=23.0
Requires-Dist: pathlib2>=2.3.0
Requires-Dist: pyyaml>=6.0.0
Requires-Dist: requests>=2.31.0
Requires-Dist: rich>=13.0.0
Provides-Extra: dev
Requires-Dist: black>=23.0.0; extra == 'dev'
Requires-Dist: build>=0.10.0; extra == 'dev'
Requires-Dist: flake8>=6.0.0; extra == 'dev'
Requires-Dist: isort>=5.12.0; extra == 'dev'
Requires-Dist: mypy>=1.0.0; extra == 'dev'
Requires-Dist: pre-commit>=3.0.0; extra == 'dev'
Requires-Dist: pytest-cov>=4.0.0; extra == 'dev'
Requires-Dist: pytest-mock>=3.10.0; extra == 'dev'
Requires-Dist: pytest>=7.0.0; extra == 'dev'
Requires-Dist: twine>=4.0.0; extra == 'dev'
Provides-Extra: test
Requires-Dist: pytest-cov>=4.0.0; extra == 'test'
Requires-Dist: pytest-mock>=3.10.0; extra == 'test'
Requires-Dist: pytest-timeout>=2.1.0; extra == 'test'
Requires-Dist: pytest>=7.0.0; extra == 'test'
Requires-Dist: tox>=4.0.0; extra == 'test'
